{"cameraMode":{"drawMode":0,"name":"Shaded","section":"Shading Mode"},"sceneLighting":true,"audioPlay":false,"sceneViewState":{"m_AlwaysRefresh":false,"showFog":true,"showSkybox":true,"showFlares":true,"showImageEffects":true,"showParticleSystems":true,"showVisualEffectGraphs":true,"m_FxEnabled":true},"in2DMode":false,"pivot":{"x":3.0027050971984865,"y":-54.2942008972168,"z":126.44796752929688},"rotation":{"x":0.21149414777755738,"y":0.042804259806871417,"z":-0.00929428730159998,"w":0.9764085412025452},"size":82.21410369873047,"orthographic":false}